{
  "info": {
    "name": "Studify - Mobile Student API",
    "description": "Complete API collection for Student mobile app\n\nAll endpoints require authentication with Bearer token.\nSet the 'token' variable after login.\n\nNote: Login and Profile endpoints now return 'username' field extracted from user profile (Student.name, Doctor.name, etc.).",
    "schema": "https://schema.getpostman.com/json/collection/v2.1.0/collection.json",
    "_exporter_id": "studify-mobile-student",
    "version": "1.1.0"
  },
  "item": [
    {
      "name": "Auth",
      "item": [
        {
          "name": "Register",
          "request": {
            "method": "POST",
            "header": [
              {
                "key": "Content-Type",
                "value": "application/json"
              }
            ],
            "body": {
              "mode": "raw",
              "raw": "{\n  \"phone\": \"+1234567890\",\n  \"password\": \"Password123!\",\n  \"repeatPassword\": \"Password123!\",\n  \"type\": \"STUDENT\",\n  \"email\": \"student@example.com\",\n  \"name\": \"Student Name\",\n  \"nameAr\": \"اسم الطالب\",\n  \"nameEn\": \"Student Name\",\n  \"collegeId\": \"college-uuid-here\",\n  \"departmentId\": \"department-uuid-here\"\n}",
              "options": {
                "raw": {
                  "language": "json"
                }
              }
            },
            "url": {
              "raw": "{{base_url}}/auth/register",
              "host": [
                "{{base_url}}"
              ],
              "path": [
                "auth",
                "register"
              ]
            }
          }
        },
        {
          "name": "Login",
          "request": {
            "method": "POST",
            "header": [
              {
                "key": "Content-Type",
                "value": "application/json"
              }
            ],
            "body": {
              "mode": "raw",
              "raw": "{\n  \"phone\": \"+1234567890\",\n  \"password\": \"Password123!\",\n  \"clientType\": \"STUDENT\"\n}"
            },
            "url": {
              "raw": "{{base_url}}/auth/login",
              "host": [
                "{{base_url}}"
              ],
              "path": [
                "auth",
                "login"
              ]
            },
            "event": [
              {
                "listen": "test",
                "script": {
                  "exec": [
                    "if (pm.response.code === 200) {",
                    "    var jsonData = pm.response.json();",
                    "    if (jsonData.data && jsonData.data.token) {",
                    "        pm.collectionVariables.set(\"token\", jsonData.data.token);",
                    "        console.log(\"Token saved to collection variable\");",
                    "    }",
                    "}"
                  ],
                  "type": "text/javascript"
                }
              }
            ]
          }
        },
        {
          "name": "Verify OTP",
          "request": {
            "method": "POST",
            "header": [
              {
                "key": "Content-Type",
                "value": "application/json"
              }
            ],
            "body": {
              "mode": "raw",
              "raw": "{\n  \"userId\": \"user-uuid-here\",\n  \"code\": \"123456\"\n}"
            },
            "url": {
              "raw": "{{base_url}}/auth/verify-otp",
              "host": [
                "{{base_url}}"
              ],
              "path": [
                "auth",
                "verify-otp"
              ]
            }
          }
        },
        {
          "name": "Resend OTP",
          "request": {
            "method": "POST",
            "header": [
              {
                "key": "Content-Type",
                "value": "application/json"
              }
            ],
            "body": {
              "mode": "raw",
              "raw": "{\n  \"userId\": \"user-uuid-here\"\n}"
            },
            "url": {
              "raw": "{{base_url}}/auth/resend-otp",
              "host": [
                "{{base_url}}"
              ],
              "path": [
                "auth",
                "resend-otp"
              ]
            }
          }
        },
        {
          "name": "Forgot Password",
          "request": {
            "method": "POST",
            "header": [
              {
                "key": "Content-Type",
                "value": "application/json"
              }
            ],
            "body": {
              "mode": "raw",
              "raw": "{\n  \"phone\": \"+1234567890\"\n}"
            },
            "url": {
              "raw": "{{base_url}}/auth/forgot-password",
              "host": [
                "{{base_url}}"
              ],
              "path": [
                "auth",
                "forgot-password"
              ]
            }
          }
        },
        {
          "name": "Reset Password",
          "request": {
            "method": "POST",
            "header": [
              {
                "key": "Content-Type",
                "value": "application/json"
              }
            ],
            "body": {
              "mode": "raw",
              "raw": "{\n  \"userId\": \"user-uuid-here\",\n  \"code\": \"123456\",\n  \"newPassword\": \"NewPassword123!\"\n}"
            },
            "url": {
              "raw": "{{base_url}}/auth/reset-password",
              "host": [
                "{{base_url}}"
              ],
              "path": [
                "auth",
                "reset-password"
              ]
            }
          }
        }
      ]
    },
    {
      "name": "Public",
      "item": [
        {
          "name": "Get Colleges",
          "request": {
            "method": "GET",
            "header": [],
            "url": {
              "raw": "{{base_url}}/api/colleges",
              "host": [
                "{{base_url}}"
              ],
              "path": [
                "api",
                "colleges"
              ]
            },
            "description": "Get all colleges (public endpoint - no authentication required). Use this to get collegeId for registration."
          }
        },
        {
          "name": "Get College by ID",
          "request": {
            "method": "GET",
            "header": [],
            "url": {
              "raw": "{{base_url}}/api/colleges/:id",
              "host": [
                "{{base_url}}"
              ],
              "path": [
                "api",
                "colleges",
                ":id"
              ],
              "variable": [
                {
                  "key": "id",
                  "value": "college-uuid-here"
                }
              ]
            },
            "description": "Get a specific college by ID (public endpoint - no authentication required)."
          }
        },
        {
          "name": "Get Departments",
          "request": {
            "method": "GET",
            "header": [],
            "url": {
              "raw": "{{base_url}}/api/departments?collegeId=college-uuid-here",
              "host": [
                "{{base_url}}"
              ],
              "path": [
                "api",
                "departments"
              ],
              "query": [
                {
                  "key": "collegeId",
                  "value": "college-uuid-here",
                  "description": "Filter departments by college ID"
                },
                {
                  "key": "page",
                  "value": "1",
                  "disabled": true
                },
                {
                  "key": "limit",
                  "value": "10",
                  "disabled": true
                },
                {
                  "key": "search",
                  "value": "",
                  "disabled": true
                }
              ]
            },
            "description": "Get all departments (public endpoint - no authentication required). Use collegeId query parameter to filter by college. Use this to get departmentId for registration."
          }
        },
        {
          "name": "Get Department by ID",
          "request": {
            "method": "GET",
            "header": [],
            "url": {
              "raw": "{{base_url}}/api/departments/:id",
              "host": [
                "{{base_url}}"
              ],
              "path": [
                "api",
                "departments",
                ":id"
              ],
              "variable": [
                {
                  "key": "id",
                  "value": "department-uuid-here"
                }
              ]
            },
            "description": "Get a specific department by ID (public endpoint - no authentication required)."
          }
        }
      ]
    },
    {
      "name": "Profile",
      "item": [
        {
          "name": "Get Profile",
          "request": {
            "method": "GET",
            "header": [
              {
                "key": "Authorization",
                "value": "Bearer {{token}}"
              }
            ],
            "url": {
              "raw": "{{base_url}}/mobile/student/profile",
              "host": [
                "{{base_url}}"
              ],
              "path": [
                "mobile",
                "student",
                "profile"
              ]
            }
          }
        },
        {
          "name": "Update Profile",
          "request": {
            "method": "PUT",
            "header": [
              {
                "key": "Authorization",
                "value": "Bearer {{token}}"
              },
              {
                "key": "Content-Type",
                "value": "application/json"
              }
            ],
            "body": {
              "mode": "raw",
              "raw": "{\n  \"email\": \"newemail@example.com\",\n  \"avatarUrl\": \"https://example.com/avatar.jpg\"\n}"
            },
            "url": {
              "raw": "{{base_url}}/mobile/student/profile",
              "host": [
                "{{base_url}}"
              ],
              "path": [
                "mobile",
                "student",
                "profile"
              ]
            }
          }
        },
        {
          "name": "Update Student Profile",
          "request": {
            "method": "PUT",
            "header": [
              {
                "key": "Authorization",
                "value": "Bearer {{token}}"
              },
              {
                "key": "Content-Type",
                "value": "application/json"
              }
            ],
            "body": {
              "mode": "raw",
              "raw": "{\n  \"name\": \"Updated Name\",\n  \"collegeId\": \"college-uuid-here\",\n  \"departmentId\": \"department-uuid-here\"\n}"
            },
            "url": {
              "raw": "{{base_url}}/mobile/student/profile/student",
              "host": [
                "{{base_url}}"
              ],
              "path": [
                "mobile",
                "student",
                "profile",
                "student"
              ]
            }
          }
        },
        {
          "name": "Upload Profile Avatar",
          "request": {
            "method": "POST",
            "header": [
              {
                "key": "Authorization",
                "value": "Bearer {{token}}"
              }
            ],
            "body": {
              "mode": "formdata",
              "formdata": [
                {
                  "key": "avatar",
                  "type": "file",
                  "src": []
                }
              ]
            },
            "url": {
              "raw": "{{base_url}}/mobile/student/profile/avatar",
              "host": [
                "{{base_url}}"
              ],
              "path": [
                "mobile",
                "student",
                "profile",
                "avatar"
              ]
            }
          }
        },
        {
          "name": "Change Password",
          "request": {
            "method": "POST",
            "header": [
              {
                "key": "Authorization",
                "value": "Bearer {{token}}"
              },
              {
                "key": "Content-Type",
                "value": "application/json"
              }
            ],
            "body": {
              "mode": "raw",
              "raw": "{\n  \"currentPassword\": \"OldPassword123!\",\n  \"newPassword\": \"NewPassword123!\"\n}"
            },
            "url": {
              "raw": "{{base_url}}/mobile/student/change-password",
              "host": [
                "{{base_url}}"
              ],
              "path": [
                "mobile",
                "student",
                "change-password"
              ]
            }
          }
        },
        {
          "name": "Delete Account",
          "request": {
            "method": "DELETE",
            "header": [
              {
                "key": "Authorization",
                "value": "Bearer {{token}}"
              }
            ],
            "url": {
              "raw": "{{base_url}}/mobile/student/profile",
              "host": [
                "{{base_url}}"
              ],
              "path": [
                "mobile",
                "student",
                "profile"
              ]
            }
          }
        }
      ]
    },
    {
      "name": "Books",
      "item": [
        {
          "name": "Get Books",
          "request": {
            "method": "GET",
            "header": [
              {
                "key": "Authorization",
                "value": "Bearer {{token}}"
              }
            ],
            "url": {
              "raw": "{{base_url}}/mobile/student/books?page=1&limit=10",
              "host": [
                "{{base_url}}"
              ],
              "path": [
                "mobile",
                "student",
                "books"
              ],
              "query": [
                {
                  "key": "page",
                  "value": "1"
                },
                {
                  "key": "limit",
                  "value": "10"
                },
                {
                  "key": "categoryId",
                  "value": "",
                  "disabled": true
                },
                {
                  "key": "collegeId",
                  "value": "",
                  "disabled": true
                },
                {
                  "key": "departmentId",
                  "value": "",
                  "disabled": true
                },
                {
                  "key": "search",
                  "value": "",
                  "disabled": true
                }
              ]
            }
          }
        },
        {
          "name": "Get Book by ID",
          "request": {
            "method": "GET",
            "header": [
              {
                "key": "Authorization",
                "value": "Bearer {{token}}"
              }
            ],
            "url": {
              "raw": "{{base_url}}/mobile/student/books/:id",
              "host": [
                "{{base_url}}"
              ],
              "path": [
                "mobile",
                "student",
                "books",
                ":id"
              ],
              "variable": [
                {
                  "key": "id",
                  "value": "book-uuid-here"
                }
              ]
            }
          }
        },
        {
          "name": "Create Content Order - Book Access",
          "request": {
            "method": "POST",
            "header": [
              {
                "key": "Authorization",
                "value": "Bearer {{token}}"
              },
              {
                "key": "Content-Type",
                "value": "application/json"
              }
            ],
            "body": {
              "mode": "raw",
              "raw": "{\n  \"accessType\": \"READ\",\n  \"address\": \"12 Nile Corniche, Maadi, Cairo\",\n  \"latitude\": 30.0444,\n  \"longitude\": 31.2357\n}",
              "options": {
                "raw": {
                  "language": "json"
                }
              }
            },
            "url": {
              "raw": "{{base_url}}/mobile/student/books/:bookId/access",
              "host": [
                "{{base_url}}"
              ],
              "path": [
                "mobile",
                "student",
                "books",
                ":bookId",
                "access"
              ],
              "variable": [
                {
                  "key": "bookId",
                  "value": "book-uuid-here"
                }
              ]
            },
            "description": "Create a CONTENT order for a book. Optional: address, latitude, longitude (customer delivery location for map/tracking)."
          }
        }
      ]
    },
    {
      "name": "Products",
      "item": [
        {
          "name": "Get Products",
          "request": {
            "method": "GET",
            "header": [
              {
                "key": "Authorization",
                "value": "Bearer {{token}}"
              }
            ],
            "url": {
              "raw": "{{base_url}}/mobile/student/products?page=1&limit=10",
              "host": [
                "{{base_url}}"
              ],
              "path": [
                "mobile",
                "student",
                "products"
              ],
              "query": [
                {
                  "key": "page",
                  "value": "1"
                },
                {
                  "key": "limit",
                  "value": "10"
                },
                {
                  "key": "categoryId",
                  "value": "",
                  "disabled": true
                },
                {
                  "key": "collegeId",
                  "value": "",
                  "disabled": true
                },
                {
                  "key": "search",
                  "value": "",
                  "disabled": true
                }
              ]
            }
          }
        },
        {
          "name": "Get Product by ID",
          "request": {
            "method": "GET",
            "header": [
              {
                "key": "Authorization",
                "value": "Bearer {{token}}"
              }
            ],
            "url": {
              "raw": "{{base_url}}/mobile/student/products/:id",
              "host": [
                "{{base_url}}"
              ],
              "path": [
                "mobile",
                "student",
                "products",
                ":id"
              ],
              "variable": [
                {
                  "key": "id",
                  "value": "product-uuid-here"
                }
              ]
            }
          }
        }
      ]
    },
    {
      "name": "Materials",
      "item": [
        {
          "name": "Get Materials",
          "request": {
            "method": "GET",
            "header": [
              {
                "key": "Authorization",
                "value": "Bearer {{token}}"
              }
            ],
            "url": {
              "raw": "{{base_url}}/mobile/student/materials?page=1&limit=10",
              "host": ["{{base_url}}"],
              "path": ["mobile", "student", "materials"],
              "query": [
                {
                  "key": "page",
                  "value": "1"
                },
                {
                  "key": "limit",
                  "value": "10"
                },
                {
                  "key": "categoryId",
                  "value": "",
                  "disabled": true
                },
                {
                  "key": "collegeId",
                  "value": "",
                  "disabled": true
                },
                {
                  "key": "departmentId",
                  "value": "",
                  "disabled": true
                },
                {
                  "key": "materialType",
                  "value": "",
                  "disabled": true
                },
                {
                  "key": "search",
                  "value": "",
                  "disabled": true
                }
              ]
            }
          }
        },
        {
          "name": "Get Material by ID",
          "request": {
            "method": "GET",
            "header": [
              {
                "key": "Authorization",
                "value": "Bearer {{token}}"
              }
            ],
            "url": {
              "raw": "{{base_url}}/mobile/student/materials/:id",
              "host": ["{{base_url}}"],
              "path": ["mobile", "student", "materials", ":id"],
              "variable": [
                {
                  "key": "id",
                  "value": "material-uuid-here"
                }
              ]
            }
          }
        },
        {
          "name": "Increment Material Downloads",
          "request": {
            "method": "POST",
            "header": [
              {
                "key": "Authorization",
                "value": "Bearer {{token}}"
              }
            ],
            "url": {
              "raw": "{{base_url}}/mobile/student/materials/:id/download",
              "host": ["{{base_url}}"],
              "path": ["mobile", "student", "materials", ":id", "download"],
              "variable": [
                {
                  "key": "id",
                  "value": "material-uuid-here"
                }
              ]
            }
          }
        }
      ]
    },
    {
      "name": "Categories",
      "item": [
        {
          "name": "Get Book Categories",
          "request": {
            "method": "GET",
            "header": [
              {
                "key": "Authorization",
                "value": "Bearer {{token}}"
              }
            ],
            "url": {
              "raw": "{{base_url}}/mobile/categories/books",
              "host": [
                "{{base_url}}"
              ],
              "path": [
                "mobile",
                "student",
                "categories",
                "books"
              ]
            }
          }
        },
        {
          "name": "Get Product Categories",
          "request": {
            "method": "GET",
            "header": [
              {
                "key": "Authorization",
                "value": "Bearer {{token}}"
              }
            ],
            "url": {
              "raw": "{{base_url}}/mobile/categories/products",
              "host": [
                "{{base_url}}"
              ],
              "path": [
                "mobile",
                "student",
                "categories",
                "products"
              ]
            }
          }
        }
      ]
    },
    {
      "name": "Colleges & Departments",
      "item": [
        {
          "name": "Get Colleges",
          "request": {
            "method": "GET",
            "header": [
              {
                "key": "Authorization",
                "value": "Bearer {{token}}"
              }
            ],
            "url": {
              "raw": "{{base_url}}/mobile/colleges?page=1&limit=10",
              "host": [
                "{{base_url}}"
              ],
              "path": [
                "mobile",
                "student",
                "colleges"
              ],
              "query": [
                {
                  "key": "page",
                  "value": "1"
                },
                {
                  "key": "limit",
                  "value": "10"
                },
                {
                  "key": "search",
                  "value": "",
                  "disabled": true
                }
              ]
            }
          }
        },
        {
          "name": "Get College by ID",
          "request": {
            "method": "GET",
            "header": [
              {
                "key": "Authorization",
                "value": "Bearer {{token}}"
              }
            ],
            "url": {
              "raw": "{{base_url}}/mobile/colleges/:id",
              "host": [
                "{{base_url}}"
              ],
              "path": [
                "mobile",
                "student",
                "colleges",
                ":id"
              ],
              "variable": [
                {
                  "key": "id",
                  "value": "college-uuid-here"
                }
              ]
            }
          }
        },
        {
          "name": "Get Departments",
          "request": {
            "method": "GET",
            "header": [
              {
                "key": "Authorization",
                "value": "Bearer {{token}}"
              }
            ],
            "url": {
              "raw": "{{base_url}}/mobile/departments?page=1&limit=10",
              "host": [
                "{{base_url}}"
              ],
              "path": [
                "mobile",
                "student",
                "departments"
              ],
              "query": [
                {
                  "key": "page",
                  "value": "1"
                },
                {
                  "key": "limit",
                  "value": "10"
                },
                {
                  "key": "collegeId",
                  "value": "",
                  "disabled": true
                },
                {
                  "key": "search",
                  "value": "",
                  "disabled": true
                }
              ]
            }
          }
        }
      ]
    },
    {
      "name": "Print Center",
      "item": [
        {
          "name": "Get Print Options for Book (Global)",
          "request": {
            "method": "GET",
            "header": [
              {
                "key": "Authorization",
                "value": "Bearer {{token}}"
              }
            ],
            "url": {
              "raw": "{{base_url}}/api/mobile/:bookId/print-options?page=1&limit=10",
              "host": [
                "{{base_url}}"
              ],
              "path": [
                "api",
                "mobile",
                ":bookId",
                "print-options"
              ],
              "query": [
                {
                  "key": "page",
                  "value": "1"
                },
                {
                  "key": "limit",
                  "value": "10"
                }
              ],
              "variable": [
                {
                  "key": "bookId",
                  "value": "book-uuid-here"
                }
              ]
            },
            "description": "Global endpoint: get all enabled print options for a book. :bookId = book UUID."
          }
        },
        {
          "name": "Get Print Options for Material (Global)",
          "request": {
            "method": "GET",
            "header": [
              {
                "key": "Authorization",
                "value": "Bearer {{token}}"
              }
            ],
            "url": {
              "raw": "{{base_url}}/api/mobile/:materialId/print-options?page=1&limit=10",
              "host": [
                "{{base_url}}"
              ],
              "path": [
                "api",
                "mobile",
                ":materialId",
                "print-options"
              ],
              "query": [
                {
                  "key": "page",
                  "value": "1"
                },
                {
                  "key": "limit",
                  "value": "10"
                }
              ],
              "variable": [
                {
                  "key": "materialId",
                  "value": "material-uuid-here"
                }
              ]
            },
            "description": "Global endpoint: get all enabled print options for a material. :materialId = material UUID."
          }
        },
        {
          "name": "Get All Print Options (Student list)",
          "request": {
            "method": "GET",
            "header": [
              {
                "key": "Authorization",
                "value": "Bearer {{token}}"
              }
            ],
            "url": {
              "raw": "{{base_url}}/api/mobile/student/print-options?page=1&limit=10",
              "host": [
                "{{base_url}}"
              ],
              "path": [
                "api",
                "mobile",
                "student",
                "print-options"
              ],
              "query": [
                {
                  "key": "page",
                  "value": "1"
                },
                {
                  "key": "limit",
                  "value": "10"
                },
                {
                  "key": "bookId",
                  "value": "",
                  "disabled": true
                },
                {
                  "key": "materialId",
                  "value": "",
                  "disabled": true
                },
                {
                  "key": "hasUploadedFile",
                  "value": "",
                  "disabled": true,
                  "description": "Filter by uploaded files: 'true' or 'false'"
                }
              ]
            },
            "description": "Get all print options. Filter by bookId, materialId, or hasUploadedFile."
          }
        },
        {
          "name": "Get Print Option by ID",
          "request": {
            "method": "GET",
            "header": [
              {
                "key": "Authorization",
                "value": "Bearer {{token}}"
              }
            ],
            "url": {
              "raw": "{{base_url}}/api/mobile/student/print-options/:id",
              "host": [
                "{{base_url}}"
              ],
              "path": [
                "api",
                "mobile",
                "student",
                "print-options",
                ":id"
              ],
              "variable": [
                {
                  "key": "id",
                  "value": "print-option-uuid-here"
                }
              ]
            }
          }
        },
        {
          "name": "Get Print Quote",
          "request": {
            "method": "GET",
            "header": [
              {
                "key": "Authorization",
                "value": "Bearer {{token}}"
              }
            ],
            "url": {
              "raw": "{{base_url}}/api/mobile/student/print-options/:id/quote",
              "host": [
                "{{base_url}}"
              ],
              "path": [
                "api",
                "mobile",
                "student",
                "print-options",
                ":id",
                "quote"
              ],
              "variable": [
                {
                  "key": "id",
                  "value": "print-option-uuid-here"
                }
              ]
            },
            "description": "Get pricing quote for a print option. Returns total price based on the print option's configuration (copies, paperType, colorType, doubleSide)."
          }
        },
        {
          "name": "Create Print Order from Print Option",
          "request": {
            "method": "POST",
            "header": [
              {
                "key": "Authorization",
                "value": "Bearer {{token}}"
              }
            ],
            "url": {
              "raw": "{{base_url}}/api/mobile/student/print-options/:id/order",
              "host": [
                "{{base_url}}"
              ],
              "path": [
                "api",
                "mobile",
                "student",
                "print-options",
                ":id",
                "order"
              ],
              "variable": [
                {
                  "key": "id",
                  "value": "print-option-uuid-here"
                }
              ]
            },
            "description": "Create an order from a print option. The print option must already exist with all configuration (copies, paperType, colorType, doubleSide)."
          }
        },
        {
          "name": "Upload File and Create Print Option",
          "request": {
            "method": "POST",
            "header": [
              {
                "key": "Authorization",
                "value": "Bearer {{token}}"
              }
            ],
            "body": {
              "mode": "formdata",
              "formdata": [
                {
                  "key": "file",
                  "type": "file",
                  "src": []
                },
                {
                  "key": "colorType",
                  "value": "COLOR",
                  "type": "text"
                },
                {
                  "key": "copies",
                  "value": "1",
                  "type": "text"
                },
                {
                  "key": "paperType",
                  "value": "A4",
                  "type": "text"
                },
                {
                  "key": "doubleSide",
                  "value": "false",
                  "type": "text"
                },
                {
                  "key": "totalPages",
                  "value": "50",
                  "type": "text",
                  "description": "Optional: Number of pages in the uploaded file"
                }
              ]
            },
            "url": {
              "raw": "{{base_url}}/api/mobile/print-center/upload",
              "host": [
                "{{base_url}}"
              ],
              "path": [
                "api",
                "mobile",
                "print-center",
                "upload"
              ]
            },
            "description": "Upload a file (PDF/DOC) and create a print option. File will be uploaded and URL will be saved automatically. Returns the created print option with uploadedFileUrl."
          }
        },
        {
          "name": "Create Print Option - Book",
          "request": {
            "method": "POST",
            "header": [
              {
                "key": "Authorization",
                "value": "Bearer {{token}}"
              },
              {
                "key": "Content-Type",
                "value": "application/json"
              }
            ],
            "body": {
              "mode": "raw",
              "raw": "{\n  \"colorType\": \"COLOR\",\n  \"copies\": 1,\n  \"paperType\": \"A4\",\n  \"doubleSide\": false\n}",
              "options": {
                "raw": {
                  "language": "json"
                }
              }
            },
            "url": {
              "raw": "{{base_url}}/api/mobile/print-center/book/:bookId",
              "host": [
                "{{base_url}}"
              ],
              "path": [
                "api",
                "mobile",
                "print-center",
                "book",
                ":bookId"
              ],
              "variable": [
                {
                  "key": "bookId",
                  "value": "book-uuid-here"
                }
              ]
            },
            "description": "Create a print option for a book. Book ID is in the URL path."
          }
        },
        {
          "name": "Create Print Option - Material",
          "request": {
            "method": "POST",
            "header": [
              {
                "key": "Authorization",
                "value": "Bearer {{token}}"
              },
              {
                "key": "Content-Type",
                "value": "application/json"
              }
            ],
            "body": {
              "mode": "raw",
              "raw": "{\n  \"colorType\": \"BLACK_WHITE\",\n  \"copies\": 3,\n  \"paperType\": \"A4\",\n  \"doubleSide\": true\n}",
              "options": {
                "raw": {
                  "language": "json"
                }
              }
            },
            "url": {
              "raw": "{{base_url}}/api/mobile/print-center/material/:materialId",
              "host": [
                "{{base_url}}"
              ],
              "path": [
                "api",
                "mobile",
                "print-center",
                "material",
                ":materialId"
              ],
              "variable": [
                {
                  "key": "materialId",
                  "value": "material-uuid-here"
                }
              ]
            },
            "description": "Create a print option for a material. Material ID is in the URL path."
          }
        },
        {
          "name": "Create Content Order - Material Access",
          "request": {
            "method": "POST",
            "header": [
              {
                "key": "Authorization",
                "value": "Bearer {{token}}"
              },
              {
                "key": "Content-Type",
                "value": "application/json"
              }
            ],
            "body": {
              "mode": "raw",
              "raw": "{\n  \"accessType\": \"READ\",\n  \"address\": \"45 El-Nasr Rd, Nasr City, Cairo\",\n  \"latitude\": 30.0626,\n  \"longitude\": 31.2497\n}",
              "options": {
                "raw": {
                  "language": "json"
                }
              }
            },
            "url": {
              "raw": "{{base_url}}/mobile/student/materials/:materialId/access",
              "host": [
                "{{base_url}}"
              ],
              "path": [
                "mobile",
                "student",
                "materials",
                ":materialId",
                "access"
              ],
              "variable": [
                {
                  "key": "materialId",
                  "value": "material-uuid-here"
                }
              ]
            },
            "description": "Create a CONTENT order for a material. Optional: address, latitude, longitude (customer delivery location for map/tracking)."
          }
        }
      ]
    },
    {
      "name": "Orders",
      "item": [
        {
          "name": "Get My Orders",
          "request": {
            "method": "GET",
            "header": [
              {
                "key": "Authorization",
                "value": "Bearer {{token}}"
              }
            ],
            "url": {
              "raw": "{{base_url}}/mobile/student/orders?page=1&limit=10",
              "host": [
                "{{base_url}}"
              ],
              "path": [
                "mobile",
                "student",
                "orders"
              ],
              "query": [
                {
                  "key": "page",
                  "value": "1"
                },
                {
                  "key": "limit",
                  "value": "10"
                },
                {
                  "key": "status",
                  "value": "",
                  "disabled": true
                }
              ]
            }
          }
        },
        {
          "name": "Get Order by ID",
          "request": {
            "method": "GET",
            "header": [
              {
                "key": "Authorization",
                "value": "Bearer {{token}}"
              }
            ],
            "url": {
              "raw": "{{base_url}}/mobile/student/orders/:id",
              "host": [
                "{{base_url}}"
              ],
              "path": [
                "mobile",
                "student",
                "orders",
                ":id"
              ],
              "variable": [
                {
                  "key": "id",
                  "value": "order-uuid-here"
                }
              ]
            }
          }
        },
        {
          "name": "Create Order",
          "request": {
            "method": "POST",
            "header": [
              {
                "key": "Authorization",
                "value": "Bearer {{token}}"
              },
              {
                "key": "Content-Type",
                "value": "application/json"
              }
            ],
            "body": {
              "mode": "raw",
              "raw": "{\n  \"items\": [\n    {\n      \"referenceType\": \"PRODUCT\",\n      \"referenceId\": \"550e8400-e29b-41d4-a716-446655440000\",\n      \"quantity\": 2,\n      \"price\": 25.0\n    },\n    {\n      \"referenceType\": \"PRODUCT\",\n      \"referenceId\": \"660e8400-e29b-41d4-a716-446655440001\",\n      \"quantity\": 1,\n      \"price\": 30.0\n    }\n  ],\n  \"address\": \"123 University St, Cairo\",\n  \"latitude\": 30.0444,\n  \"longitude\": 31.2357\n}",
              "options": {
                "raw": {
                  "language": "json"
                }
              }
            },
            "url": {
              "raw": "{{base_url}}/mobile/student/orders",
              "host": [
                "{{base_url}}"
              ],
              "path": [
                "mobile",
                "student",
                "orders"
              ]
            },
            "description": "Create a PRODUCT order (cart). Optional: address, latitude, longitude (delivery location for map/tracking). For BOOK/MATERIAL use books/:bookId/access or materials/:materialId/access."
          }
        },
        {
          "name": "Confirm Payment",
          "request": {
            "method": "POST",
            "header": [
              {
                "key": "Authorization",
                "value": "Bearer {{token}}"
              },
              {
                "key": "Content-Type",
                "value": "application/json"
              }
            ],
            "body": {
              "mode": "raw",
              "raw": "{\n  \"paymentMethod\": \"CASH\"\n}",
              "options": {
                "raw": {
                  "language": "json"
                }
              }
            },
            "url": {
              "raw": "{{base_url}}/mobile/student/orders/:id/confirm-payment",
              "host": [
                "{{base_url}}"
              ],
              "path": [
                "mobile",
                "student",
                "orders",
                ":id",
                "confirm-payment"
              ],
              "variable": [
                {
                  "key": "id",
                  "value": "order-uuid-here"
                }
              ]
            },
            "description": "Confirm payment for an order (status CREATED → PAID). paymentMethod: CASH | CREDIT | PAYMENT_LINK (for web/gateway later). Sets paidAt and may trigger print center assignment."
          }
        },
        {
          "name": "Cancel Order",
          "request": {
            "method": "POST",
            "header": [
              {
                "key": "Authorization",
                "value": "Bearer {{token}}"
              }
            ],
            "url": {
              "raw": "{{base_url}}/mobile/student/orders/:id/cancel",
              "host": [
                "{{base_url}}"
              ],
              "path": [
                "mobile",
                "student",
                "orders",
                ":id",
                "cancel"
              ],
              "variable": [
                {
                  "key": "id",
                  "value": "order-uuid-here"
                }
              ]
            }
          }
        }
      ]
    },
    {
      "name": "Reviews",
      "item": [
        {
          "name": "Get Reviews",
          "request": {
            "method": "GET",
            "header": [
              {
                "key": "Authorization",
                "value": "Bearer {{token}}"
              }
            ],
            "url": {
              "raw": "{{base_url}}/mobile/student/reviews?page=1&limit=10",
              "host": [
                "{{base_url}}"
              ],
              "path": [
                "mobile",
                "student",
                "reviews"
              ],
              "query": [
                {
                  "key": "page",
                  "value": "1"
                },
                {
                  "key": "limit",
                  "value": "10"
                },
                {
                  "key": "targetId",
                  "value": "",
                  "disabled": true
                },
                {
                  "key": "targetType",
                  "value": "",
                  "disabled": true
                }
              ]
            }
          }
        },
        {
          "name": "Create Review",
          "request": {
            "method": "POST",
            "header": [
              {
                "key": "Authorization",
                "value": "Bearer {{token}}"
              },
              {
                "key": "Content-Type",
                "value": "application/json"
              }
            ],
            "body": {
              "mode": "raw",
              "raw": "{\n  \"targetId\": \"book-uuid-here\",\n  \"targetType\": \"BOOK\",\n  \"rating\": 5,\n  \"comment\": \"Great book!\"\n}"
            },
            "url": {
              "raw": "{{base_url}}/mobile/student/reviews",
              "host": [
                "{{base_url}}"
              ],
              "path": [
                "mobile",
                "student",
                "reviews"
              ]
            }
          }
        },
        {
          "name": "Update Review",
          "request": {
            "method": "PUT",
            "header": [
              {
                "key": "Authorization",
                "value": "Bearer {{token}}"
              },
              {
                "key": "Content-Type",
                "value": "application/json"
              }
            ],
            "body": {
              "mode": "raw",
              "raw": "{\n  \"rating\": 4,\n  \"comment\": \"Updated review comment\"\n}"
            },
            "url": {
              "raw": "{{base_url}}/mobile/student/reviews/:id",
              "host": [
                "{{base_url}}"
              ],
              "path": [
                "mobile",
                "student",
                "reviews",
                ":id"
              ],
              "variable": [
                {
                  "key": "id",
                  "value": "review-uuid-here"
                }
              ]
            }
          }
        },
        {
          "name": "Delete Review",
          "request": {
            "method": "DELETE",
            "header": [
              {
                "key": "Authorization",
                "value": "Bearer {{token}}"
              }
            ],
            "url": {
              "raw": "{{base_url}}/mobile/student/reviews/:id",
              "host": [
                "{{base_url}}"
              ],
              "path": [
                "mobile",
                "student",
                "reviews",
                ":id"
              ],
              "variable": [
                {
                  "key": "id",
                  "value": "review-uuid-here"
                }
              ]
            }
          }
        }
      ]
    },
    {
      "name": "Cart",
      "item": [
        {
          "name": "Get Cart",
          "request": {
            "method": "GET",
            "header": [
              {
                "key": "Authorization",
                "value": "Bearer {{token}}"
              }
            ],
            "url": {
              "raw": "{{base_url}}/mobile/cart",
              "host": ["{{base_url}}"],
              "path": ["mobile", "cart"]
            }
          }
        },
        {
          "name": "Add to Cart",
          "request": {
            "method": "POST",
            "header": [
              {
                "key": "Authorization",
                "value": "Bearer {{token}}"
              },
              {
                "key": "Content-Type",
                "value": "application/json"
              }
            ],
            "body": {
              "mode": "raw",
              "raw": "{\n  \"referenceType\": \"BOOK\",\n  \"referenceId\": \"book-uuid-here\",\n  \"quantity\": 1\n}"
            },
            "url": {
              "raw": "{{base_url}}/mobile/cart/items",
              "host": ["{{base_url}}"],
              "path": ["mobile", "cart", "items"]
            }
          }
        },
        {
          "name": "Update Cart Item",
          "request": {
            "method": "PUT",
            "header": [
              {
                "key": "Authorization",
                "value": "Bearer {{token}}"
              },
              {
                "key": "Content-Type",
                "value": "application/json"
              }
            ],
            "body": {
              "mode": "raw",
              "raw": "{\n  \"quantity\": 2\n}"
            },
            "url": {
              "raw": "{{base_url}}/mobile/cart/items/:id",
              "host": ["{{base_url}}"],
              "path": ["mobile", "cart", "items", ":id"],
              "variable": [
                {
                  "key": "id",
                  "value": "cart-item-uuid-here"
                }
              ]
            }
          }
        },
        {
          "name": "Remove from Cart",
          "request": {
            "method": "DELETE",
            "header": [
              {
                "key": "Authorization",
                "value": "Bearer {{token}}"
              }
            ],
            "url": {
              "raw": "{{base_url}}/mobile/cart/items/:id",
              "host": ["{{base_url}}"],
              "path": ["mobile", "cart", "items", ":id"],
              "variable": [
                {
                  "key": "id",
                  "value": "cart-item-uuid-here"
                }
              ]
            }
          }
        },
        {
          "name": "Clear Cart",
          "request": {
            "method": "DELETE",
            "header": [
              {
                "key": "Authorization",
                "value": "Bearer {{token}}"
              }
            ],
            "url": {
              "raw": "{{base_url}}/mobile/cart",
              "host": ["{{base_url}}"],
              "path": ["mobile", "cart"]
            }
          }
        }
      ]
    },
    {
      "name": "Sliders",
      "item": [
        {
          "name": "Get Active Sliders",
          "request": {
            "method": "GET",
            "header": [],
            "url": {
              "raw": "{{base_url}}/mobile/sliders",
              "host": ["{{base_url}}"],
              "path": ["mobile", "sliders"]
            }
          }
        }
      ]
    },
    {
      "name": "Notifications",
      "item": [
        {
          "name": "Get Notifications",
          "request": {
            "method": "GET",
            "header": [
              {
                "key": "Authorization",
                "value": "Bearer {{token}}"
              }
            ],
            "url": {
              "raw": "{{base_url}}/mobile/student/notifications?page=1&limit=10",
              "host": [
                "{{base_url}}"
              ],
              "path": [
                "mobile",
                "student",
                "notifications"
              ],
              "query": [
                {
                  "key": "page",
                  "value": "1"
                },
                {
                  "key": "limit",
                  "value": "10"
                },
                {
                  "key": "isRead",
                  "value": "",
                  "disabled": true
                }
              ]
            }
          }
        },
        {
          "name": "Get Unread Count",
          "request": {
            "method": "GET",
            "header": [
              {
                "key": "Authorization",
                "value": "Bearer {{token}}"
              }
            ],
            "url": {
              "raw": "{{base_url}}/mobile/student/notifications/unread-count",
              "host": [
                "{{base_url}}"
              ],
              "path": [
                "mobile",
                "student",
                "notifications",
                "unread-count"
              ]
            }
          }
        },
        {
          "name": "Mark Notification as Read",
          "request": {
            "method": "PUT",
            "header": [
              {
                "key": "Authorization",
                "value": "Bearer {{token}}"
              }
            ],
            "url": {
              "raw": "{{base_url}}/mobile/student/notifications/:id/read",
              "host": [
                "{{base_url}}"
              ],
              "path": [
                "mobile",
                "student",
                "notifications",
                ":id",
                "read"
              ],
              "variable": [
                {
                  "key": "id",
                  "value": "notification-uuid-here"
                }
              ]
            }
          }
        },
        {
          "name": "Mark All Notifications as Read",
          "request": {
            "method": "PUT",
            "header": [
              {
                "key": "Authorization",
                "value": "Bearer {{token}}"
              }
            ],
            "url": {
              "raw": "{{base_url}}/mobile/student/notifications/read-all",
              "host": [
                "{{base_url}}"
              ],
              "path": [
                "mobile",
                "student",
                "notifications",
                "read-all"
              ]
            }
          }
        }
      ]
    }
  ],
  "variable": [
    {
      "key": "base_url",
      "value": "https://back-studify.developteam.site/api",
      "type": "string"
    },
    {
      "key": "token",
      "value": "",
      "type": "string"
    }
  ],
  "auth": {
    "type": "bearer",
    "bearer": [
      {
        "key": "token",
        "value": "{{token}}",
        "type": "string"
      }
    ]
  }
}